log_wizard/__init__.py
log_wizard/custom_loggers.py
log_wizard/logger_manager.py
tests/__init__.py
tests/test_logger_manager.py
log_wizard-1.2.0.dist-info/LICENSE
log_wizard-1.2.0.dist-info/METADATA
log_wizard-1.2.0.dist-info/WHEEL
log_wizard-1.2.0.dist-info/top_level.txt
log_wizard-1.2.0.dist-info/RECORD
