Metadata-Version: 2.1
Name: log_wizard
Version: 1.2.0
Summary: Siple logging for porject with multiple modules
Home-page: https://github.com/izharus/log_wizard
Author: izharus
Author-email: ruslan.izhakovskij@gmail.com
Keywords: python logging
Requires-Python: >=3
License-File: LICENSE
